pylipextractor/__init__.py
pylipextractor/config.py
pylipextractor/lip_extractor.py
pylipextractor-2.2.4.dist-info/licenses/LICENSE
pylipextractor-2.2.4.dist-info/METADATA
pylipextractor-2.2.4.dist-info/WHEEL
pylipextractor-2.2.4.dist-info/top_level.txt
pylipextractor-2.2.4.dist-info/RECORD
