Metadata-Version: 2.4
Name: pylipextractor
Version: 2.2.4
Summary: A Python package for robust lip frame extraction from videos using MediaPipe, featuring enhanced stability, configurable options, and customizable GPU-accelerated lossless video format conversion for VSR tasks.
Author-email: Mehrad Yaghoubi <mehradyaghoubi96@gmail.com>
Project-URL: Homepage, https://github.com/MehradYaghoubi/pylipextractor
Project-URL: Bug Tracker, https://github.com/MehradYaghoubi/pylipextractor/issues
Keywords: lip-extraction,visual-speech-recognition,mediapipe,video-processing,lip-reading,ffmpeg,video-conversion,documentation,examples
Classifier: Programming Language :: Python :: 3
Classifier: License :: OSI Approved :: MIT License
Classifier: Operating System :: OS Independent
Classifier: Development Status :: 5 - Production/Stable
Classifier: Intended Audience :: Developers
Classifier: Intended Audience :: Science/Research
Classifier: Topic :: Scientific/Engineering :: Artificial Intelligence
Classifier: Topic :: Multimedia :: Video
Requires-Python: >=3.8
License-File: LICENSE
Requires-Dist: opencv-python>=4.5.0
Requires-Dist: numpy>=1.20.0
Requires-Dist: mediapipe>=0.10.11
Requires-Dist: av>=10.0.0
Dynamic: license-file
